{
  "updated": "2025-11-09T13:31:56.492Z",
  "trends": [
    {
      "content": "明天的天氣"
    },
    {
      "content": "芬普尼"
    },
    {
      "content": "泫雅"
    },
    {
      "content": "古久保健二"
    },
    {
      "content": "cuaca besok"
    },
    {
      "content": "skt t1"
    },
    {
      "content": "thời tiết ngày mai"
    },
    {
      "content": "fmvp"
    },
    {
      "content": "陳文章"
    },
    {
      "content": "kkoma"
    },
    {
      "content": "lck"
    },
    {
      "content": "drx"
    },
    {
      "content": "motogp"
    },
    {
      "content": "atalanta vs sassuolo"
    },
    {
      "content": "張芸京"
    },
    {
      "content": "plg"
    },
    {
      "content": "lol t1"
    },
    {
      "content": "taiwan typhoon"
    },
    {
      "content": "淡水停電"
    },
    {
      "content": "象鼻隧道"
    },
    {
      "content": "普發一萬什麼時候入帳"
    },
    {
      "content": "日本 地震"
    }
  ]
}