{
  "updated": "2026-03-09T17:30:26.251Z",
  "trends": [
    {
      "content": "juan soto"
    },
    {
      "content": "徐康俊"
    },
    {
      "content": "dc"
    },
    {
      "content": "문보경"
    },
    {
      "content": "楊麗菁"
    },
    {
      "content": "美股開盤"
    },
    {
      "content": "日光節約時間"
    },
    {
      "content": "cpbl"
    },
    {
      "content": "wbc八強"
    },
    {
      "content": "融資"
    },
    {
      "content": "台灣隊"
    },
    {
      "content": "世界棒球12強賽"
    },
    {
      "content": "台股夜盤指數"
    }
  ]
}