{
  "updated": "2025-12-09T11:47:56.771Z",
  "trends": [
    {
      "content": "林益全"
    },
    {
      "content": "葉子誠"
    },
    {
      "content": "亞洲航空"
    },
    {
      "content": "青山宮"
    },
    {
      "content": "麥當勞新品"
    },
    {
      "content": "高大成"
    },
    {
      "content": "亞冠"
    },
    {
      "content": "g力昏迷"
    },
    {
      "content": "天一愛"
    },
    {
      "content": "蓝战非"
    },
    {
      "content": "柬埔寨"
    },
    {
      "content": "南韓"
    },
    {
      "content": "徐巧芯"
    },
    {
      "content": "f16"
    },
    {
      "content": "hola"
    },
    {
      "content": "airasia"
    },
    {
      "content": "福岡"
    },
    {
      "content": "坂本勇人"
    }
  ]
}