{
  "updated": "2026-05-03T15:59:45.157Z",
  "trends": [
    {
      "content": "明天的天氣"
    },
    {
      "content": "公务员"
    },
    {
      "content": "金秀賢"
    },
    {
      "content": "台北鼠患"
    },
    {
      "content": "烏克蘭"
    },
    {
      "content": "颱風"
    },
    {
      "content": "台鐵"
    },
    {
      "content": "朱孝天"
    },
    {
      "content": "ดูบอลสด"
    },
    {
      "content": "曼聯"
    },
    {
      "content": "manchester united"
    },
    {
      "content": "cuaca besok"
    },
    {
      "content": "f1 邁阿密"
    },
    {
      "content": "sinner"
    },
    {
      "content": "聯 華 電子"
    },
    {
      "content": "weather tomorrow"
    },
    {
      "content": "thời tiết ngày mai"
    },
    {
      "content": "許富凱"
    },
    {
      "content": "月亮"
    },
    {
      "content": "優霸盃"
    },
    {
      "content": "내일 날씨"
    }
  ]
}