{
  "updated": "2025-10-17T03:09:13.252Z",
  "trends": [
    {
      "content": "max scherzer"
    },
    {
      "content": "麥斯·薛澤"
    },
    {
      "content": "加熱菸"
    },
    {
      "content": "藍鳥"
    },
    {
      "content": "2408"
    },
    {
      "content": "mama 2025"
    },
    {
      "content": "和碩"
    },
    {
      "content": "至上"
    },
    {
      "content": "藍鳥水手"
    },
    {
      "content": "佐佐木朗希"
    },
    {
      "content": "owlting"
    },
    {
      "content": "南亞科"
    },
    {
      "content": "道奇 對 釀酒人"
    },
    {
      "content": "品安"
    },
    {
      "content": "dodgers vs brewers"
    },
    {
      "content": "3711"
    },
    {
      "content": "景碩"
    },
    {
      "content": "ace frehley"
    },
    {
      "content": "全國運動會"
    },
    {
      "content": "陽明海運"
    },
    {
      "content": "林家嘉"
    },
    {
      "content": "萬海"
    },
    {
      "content": "創見"
    },
    {
      "content": "魏寶生"
    },
    {
      "content": "華邦電股票"
    }
  ]
}