{
  "updated": "2026-04-06T03:37:35.813Z",
  "trends": [
    {
      "content": "拓元"
    },
    {
      "content": "雷暴"
    },
    {
      "content": "勇士 對 火箭"
    },
    {
      "content": "史蒂芬·柯瑞"
    },
    {
      "content": "市長"
    },
    {
      "content": "發票"
    },
    {
      "content": "退休金"
    },
    {
      "content": "庫珀·弗拉格"
    },
    {
      "content": "nba"
    },
    {
      "content": "金門航空站"
    },
    {
      "content": "指數股票型基金"
    },
    {
      "content": "雷霆 對 爵士"
    },
    {
      "content": "韓國股市"
    },
    {
      "content": "日本股市"
    },
    {
      "content": "盧克·肯納德"
    },
    {
      "content": "lalaport"
    },
    {
      "content": "日經指數"
    },
    {
      "content": "漢堡王"
    },
    {
      "content": "nba直播"
    },
    {
      "content": "飯店"
    },
    {
      "content": "日股"
    },
    {
      "content": "尹恩惠"
    },
    {
      "content": "curry"
    },
    {
      "content": "張愛玲"
    },
    {
      "content": "磷化銦"
    }
  ]
}