{
  "updated": "2025-11-26T11:47:33.302Z",
  "trends": [
    {
      "content": "香港大火"
    },
    {
      "content": "香港火災"
    },
    {
      "content": "abc牙醫聯盟"
    },
    {
      "content": "陳品安"
    },
    {
      "content": "何鷹鷺"
    },
    {
      "content": "高市"
    },
    {
      "content": "高市早苗"
    },
    {
      "content": "2027武統"
    },
    {
      "content": "國分太一"
    },
    {
      "content": "小巨蛋"
    },
    {
      "content": "eva green"
    },
    {
      "content": "阿布達比被抓"
    },
    {
      "content": "總統大選"
    },
    {
      "content": "順昱控股股份有限公司"
    },
    {
      "content": "亞冠"
    },
    {
      "content": "好市多網黃是誰"
    }
  ]
}