{
  "updated": "2025-12-11T06:49:46.387Z",
  "trends": [
    {
      "content": "賴佩霞"
    },
    {
      "content": "湖人對馬刺"
    },
    {
      "content": "nba"
    },
    {
      "content": "福麥國際"
    },
    {
      "content": "小禎男友"
    },
    {
      "content": "哈里森·巴恩斯"
    },
    {
      "content": "玉山銀行"
    },
    {
      "content": "lakers vs spurs"
    },
    {
      "content": "a’ja wilson"
    },
    {
      "content": "麥當勞"
    },
    {
      "content": "草莓優格"
    },
    {
      "content": "德安德烈·艾頓"
    },
    {
      "content": "迪倫·哈珀"
    },
    {
      "content": "梁家輝"
    },
    {
      "content": "桃園島語"
    },
    {
      "content": "智邦"
    }
  ]
}