{
  "updated": "2026-01-05T02:38:14.155Z",
  "trends": [
    {
      "content": "台積電"
    },
    {
      "content": "2330"
    },
    {
      "content": "群創"
    },
    {
      "content": "旺宏"
    },
    {
      "content": "永豐銀行"
    },
    {
      "content": "0056"
    },
    {
      "content": "京元電子"
    },
    {
      "content": "格陵蘭"
    },
    {
      "content": "欣興"
    },
    {
      "content": "ces"
    },
    {
      "content": "0052"
    },
    {
      "content": "2409"
    },
    {
      "content": "國王 對 公鹿"
    },
    {
      "content": "00878"
    },
    {
      "content": "湖人 對 灰熊"
    },
    {
      "content": "晶豪科"
    },
    {
      "content": "長興"
    },
    {
      "content": "ces 2026"
    },
    {
      "content": "2337"
    },
    {
      "content": "華東"
    },
    {
      "content": "熱火 對 鵜鶘"
    },
    {
      "content": "啟碁"
    },
    {
      "content": "00940"
    },
    {
      "content": "國巨"
    },
    {
      "content": "股票"
    }
  ]
}