{
  "updated": "2026-05-27T22:49:30.908Z",
  "trends": [
    {
      "content": "中國"
    },
    {
      "content": "臺北 市長"
    },
    {
      "content": "端午 節"
    },
    {
      "content": "6月"
    },
    {
      "content": "林書逸"
    },
    {
      "content": "道瓊工業平均指數"
    },
    {
      "content": "謝金河"
    },
    {
      "content": "郵局"
    },
    {
      "content": "2026 電腦展"
    },
    {
      "content": "水晶宮"
    },
    {
      "content": "crystal palace vs rayo"
    },
    {
      "content": "檢察官"
    },
    {
      "content": "欣興電子"
    },
    {
      "content": "台鐵"
    },
    {
      "content": "台期指夜盤"
    },
    {
      "content": "meta"
    }
  ]
}