{
  "updated": "2026-02-05T16:26:51.731Z",
  "trends": [
    {
      "content": "威力彩"
    },
    {
      "content": "明天的天氣"
    },
    {
      "content": "luke kennard"
    },
    {
      "content": "比特幣"
    },
    {
      "content": "鄧紫棋演唱會"
    },
    {
      "content": "nchu"
    },
    {
      "content": "btc"
    },
    {
      "content": "ayo dosunmu"
    },
    {
      "content": "黃尚禾"
    },
    {
      "content": "qqq"
    },
    {
      "content": "美股大跌"
    },
    {
      "content": "vix"
    },
    {
      "content": "天眼浩劫"
    },
    {
      "content": "mstr"
    },
    {
      "content": "台灣彩券"
    },
    {
      "content": "以太幣"
    },
    {
      "content": "eth"
    },
    {
      "content": "豆腐媽媽"
    },
    {
      "content": "美股盤前"
    },
    {
      "content": "009805"
    },
    {
      "content": "thời tiết ngày mai"
    },
    {
      "content": "樂透開獎"
    },
    {
      "content": "今彩539開獎直播"
    },
    {
      "content": "olimpiade musim dingin 2026"
    },
    {
      "content": "任天堂"
    }
  ]
}