{
  "updated": "2025-12-14T16:36:23.751Z",
  "trends": [
    {
      "content": "林光寧"
    },
    {
      "content": "水晶宮 對 曼城"
    },
    {
      "content": "crystal palace vs man city"
    },
    {
      "content": "烏克蘭"
    },
    {
      "content": "卓榮泰"
    },
    {
      "content": "諾丁漢森林 對 熱刺"
    },
    {
      "content": "如果我不曾見過太陽結局"
    },
    {
      "content": "sogo敦化館"
    },
    {
      "content": "動力火車"
    },
    {
      "content": "熊仔"
    },
    {
      "content": "cuaca besok"
    },
    {
      "content": "bondi beach 槍擊"
    },
    {
      "content": "crystal palace đấu với man city"
    },
    {
      "content": "thời tiết ngày mai"
    },
    {
      "content": "泰勒絲"
    },
    {
      "content": "焦凡凡"
    }
  ]
}