{
  "updated": "2025-12-10T22:50:56.327Z",
  "trends": [
    {
      "content": "madrid vs man city"
    },
    {
      "content": "皇家馬德里 對 曼城"
    },
    {
      "content": "歐冠"
    },
    {
      "content": "real madrid đấu với man city"
    },
    {
      "content": "鮑爾"
    },
    {
      "content": "เรอัลมาดริด พบ แมนซิตี"
    },
    {
      "content": "甲骨文"
    },
    {
      "content": "real madrid"
    },
    {
      "content": "甲骨文財報"
    },
    {
      "content": "oracle"
    },
    {
      "content": "tlt"
    },
    {
      "content": "tsm"
    },
    {
      "content": "台積電夜盤"
    }
  ]
}