{
  "updated": "2026-01-03T08:39:46.176Z",
  "trends": [
    {
      "content": "委內瑞拉"
    },
    {
      "content": "venezuela"
    },
    {
      "content": "皮蛋多力多滋"
    },
    {
      "content": "徐欣瑩"
    },
    {
      "content": "獵魔女團快閃店"
    },
    {
      "content": "沈伯洋"
    },
    {
      "content": "邱議瑩"
    },
    {
      "content": "林岱樺"
    },
    {
      "content": "頂溪捷運站"
    },
    {
      "content": "賈·莫蘭特"
    },
    {
      "content": "勒布朗·詹姆斯"
    },
    {
      "content": "司晓迪"
    },
    {
      "content": "嘉義市長"
    },
    {
      "content": "張啟楷"
    },
    {
      "content": "林宜瑾"
    },
    {
      "content": "lakers"
    },
    {
      "content": "布蘭丁·波傑姆斯基"
    },
    {
      "content": "台新richart卡"
    }
  ]
}