{
  "updated": "2026-06-28T16:46:55.151Z",
  "trends": [
    {
      "content": "圓山保齡球館"
    },
    {
      "content": "fifa world cup 2026 bracket"
    },
    {
      "content": "0056"
    },
    {
      "content": "抵制與蔡阿嘎合作品牌"
    },
    {
      "content": "艾薇"
    },
    {
      "content": "華倫·巴菲特"
    },
    {
      "content": "高雄巨蛋"
    },
    {
      "content": "抗議"
    },
    {
      "content": "摩根 士 丹 利"
    },
    {
      "content": "max verstappen"
    },
    {
      "content": "肖戰"
    },
    {
      "content": "motogp"
    },
    {
      "content": "香港六合彩"
    }
  ]
}