{
  "updated": "2025-11-28T04:51:08.641Z",
  "trends": [
    {
      "content": "信驊"
    },
    {
      "content": "台中公車"
    },
    {
      "content": "賴智垣"
    },
    {
      "content": "亞通"
    },
    {
      "content": "徐斯儉"
    },
    {
      "content": "00981a"
    },
    {
      "content": "波若威"
    },
    {
      "content": "cme"
    },
    {
      "content": "穩懋"
    },
    {
      "content": "台虹"
    },
    {
      "content": "徐千京"
    },
    {
      "content": "華星光"
    },
    {
      "content": "兆赫"
    },
    {
      "content": "淡水 停水"
    },
    {
      "content": "淡江大橋"
    },
    {
      "content": "2449"
    },
    {
      "content": "停水"
    },
    {
      "content": "禾馨"
    },
    {
      "content": "張嘉郡"
    },
    {
      "content": "港幣"
    },
    {
      "content": "uq"
    },
    {
      "content": "李世強"
    },
    {
      "content": "南亞"
    },
    {
      "content": "新盛力"
    },
    {
      "content": "地價稅繳納"
    }
  ]
}