{
  "updated": "2025-09-30T07:47:47.643Z",
  "trends": [
    {
      "content": "捷運踢人"
    },
    {
      "content": "陳瑞敏"
    },
    {
      "content": "三宅"
    },
    {
      "content": "陽信銀行"
    },
    {
      "content": "貴乃花"
    },
    {
      "content": "高虹安"
    },
    {
      "content": "白種元"
    },
    {
      "content": "宜鼎"
    },
    {
      "content": "netflix"
    },
    {
      "content": "line pay"
    },
    {
      "content": "wtt"
    },
    {
      "content": "内田真礼"
    },
    {
      "content": "國泰人壽"
    },
    {
      "content": "如果我不曾見過太陽"
    },
    {
      "content": "星巴克買一送一"
    },
    {
      "content": "詹皓晴"
    },
    {
      "content": "林昀儒"
    },
    {
      "content": "三立新聞"
    },
    {
      "content": "國民年金"
    }
  ]
}