{
  "updated": "2025-10-04T14:46:56.982Z",
  "trends": [
    {
      "content": "f1"
    },
    {
      "content": "安心亞"
    },
    {
      "content": "沈春華"
    },
    {
      "content": "小泉孝太郎"
    },
    {
      "content": "樓心潼"
    },
    {
      "content": "吳宗憲"
    },
    {
      "content": "f1直播"
    },
    {
      "content": "man utd vs sunderland"
    },
    {
      "content": "แมนยู พบ ซันเดอร์แลนด์"
    },
    {
      "content": "阿宗麵線"
    },
    {
      "content": "曾博恩"
    },
    {
      "content": "曼聯 對 桑德蘭"
    },
    {
      "content": "man utd đấu với sunderland"
    },
    {
      "content": "商竣程"
    },
    {
      "content": "f1 排位賽"
    },
    {
      "content": "陳榮泉"
    },
    {
      "content": "arsenal vs west ham"
    },
    {
      "content": "輝達總部"
    },
    {
      "content": "美秀集團"
    },
    {
      "content": "煙火"
    },
    {
      "content": "許願吧,精靈"
    },
    {
      "content": "xsmb"
    },
    {
      "content": "愛爾達"
    },
    {
      "content": "539號碼"
    },
    {
      "content": "袁光麟"
    }
  ]
}