{
  "updated": "2025-12-28T16:38:00.680Z",
  "trends": [
    {
      "content": "陽光女子合唱團"
    },
    {
      "content": "台中跨年"
    },
    {
      "content": "六合彩"
    },
    {
      "content": "陳水扁"
    },
    {
      "content": "周杰倫"
    },
    {
      "content": "公益律師"
    },
    {
      "content": "陳華"
    },
    {
      "content": "黃捷"
    },
    {
      "content": "sydney sweeney"
    },
    {
      "content": "milan vs verona"
    },
    {
      "content": "宮古島"
    },
    {
      "content": "heated rivalry"
    }
  ]
}