{
  "updated": "2025-10-15T04:33:16.557Z",
  "trends": [
    {
      "content": "山本由伸"
    },
    {
      "content": "秀泰"
    },
    {
      "content": "北車通緝犯"
    },
    {
      "content": "中信兄弟"
    },
    {
      "content": "林益全"
    },
    {
      "content": "太子集團"
    },
    {
      "content": "2887"
    },
    {
      "content": "大巨蛋秀泰影城"
    },
    {
      "content": "台積電法說會"
    },
    {
      "content": "旺矽"
    },
    {
      "content": "陳德容"
    },
    {
      "content": "雙鴻"
    },
    {
      "content": "星宇航空線上旅展"
    },
    {
      "content": "竹北華德福幼兒園"
    },
    {
      "content": "sam altman"
    },
    {
      "content": "jo1"
    },
    {
      "content": "高力"
    },
    {
      "content": "景碩"
    },
    {
      "content": "6282"
    },
    {
      "content": "2481"
    },
    {
      "content": "2609"
    },
    {
      "content": "宇瞻"
    },
    {
      "content": "溫妮男友"
    },
    {
      "content": "飛宏"
    },
    {
      "content": "星雲電腦"
    }
  ]
}