{
  "updated": "2026-07-12T07:13:58.574Z",
  "trends": [
    {
      "content": "孫"
    },
    {
      "content": "熱帶 擾動"
    },
    {
      "content": "巴 威 大陸"
    },
    {
      "content": "林安可"
    },
    {
      "content": "遺產"
    },
    {
      "content": "羈押"
    },
    {
      "content": "npb"
    },
    {
      "content": "四國菁英棒球對抗賽"
    },
    {
      "content": "7 12 垃圾 車"
    },
    {
      "content": "賴清德"
    },
    {
      "content": "conor mcgregor"
    },
    {
      "content": "梅西"
    },
    {
      "content": "lindsey graham"
    },
    {
      "content": "高頻寬記憶體"
    },
    {
      "content": "空中預警機"
    },
    {
      "content": "飢餓 遊戲"
    },
    {
      "content": "南亞 科 法 說 會"
    },
    {
      "content": "台塑企業"
    },
    {
      "content": "橄欖油"
    },
    {
      "content": "唐從聖"
    },
    {
      "content": "四強賽程表"
    },
    {
      "content": "ibon"
    },
    {
      "content": "股價"
    },
    {
      "content": "巴丹島"
    },
    {
      "content": "lionel messi"
    }
  ]
}