{
  "updated": "2025-11-16T05:47:28.029Z",
  "trends": [
    {
      "content": "台大男神"
    },
    {
      "content": "ufc322"
    },
    {
      "content": "凱爾·庫茲馬"
    },
    {
      "content": "台大雞排"
    },
    {
      "content": "尼古拉·約基奇"
    },
    {
      "content": "國父紀念館"
    },
    {
      "content": "盧卡·唐西奇"
    },
    {
      "content": "bucks vs lakers"
    },
    {
      "content": "灰狼對金塊"
    },
    {
      "content": "金塊"
    },
    {
      "content": "ufc直播"
    },
    {
      "content": "奧斯汀·里夫斯"
    },
    {
      "content": "安東尼·愛德華茲"
    },
    {
      "content": "espn nba"
    },
    {
      "content": "中油油價"
    },
    {
      "content": "冬季聯盟 2025"
    },
    {
      "content": "新社花海"
    }
  ]
}