{
  "updated": "2026-03-15T03:29:39.365Z",
  "trends": [
    {
      "content": "湖人 對 金塊"
    },
    {
      "content": "森下翔太"
    },
    {
      "content": "日本 委內瑞拉"
    },
    {
      "content": "伊藤大海"
    },
    {
      "content": "熱火 對 魔術"
    },
    {
      "content": "隅田知一郎"
    },
    {
      "content": "wilyer abreu"
    },
    {
      "content": "acuna jr"
    },
    {
      "content": "maikel garcia"
    },
    {
      "content": "miguel cabrera"
    },
    {
      "content": "湖人"
    },
    {
      "content": "蘭花展"
    },
    {
      "content": "nuggets vs lakers"
    },
    {
      "content": "環台賽"
    },
    {
      "content": "ranger suarez"
    },
    {
      "content": "義大利 wbc"
    },
    {
      "content": "佐佐木朗希"
    },
    {
      "content": "f1 上海"
    },
    {
      "content": "邁阿密"
    },
    {
      "content": "suarez"
    },
    {
      "content": "mlb"
    },
    {
      "content": "宋承憲"
    },
    {
      "content": "indian wells"
    },
    {
      "content": "岡本和真"
    },
    {
      "content": "丹尼爾·梅德韋傑夫"
    }
  ]
}