{
  "updated": "2025-11-29T19:24:01.790Z",
  "trends": [
    {
      "content": "孫協志"
    },
    {
      "content": "小胖老師"
    },
    {
      "content": "台南火災"
    },
    {
      "content": "red bull league of its own"
    },
    {
      "content": "99旅"
    },
    {
      "content": "花蓮火災"
    },
    {
      "content": "陸戰99旅"
    },
    {
      "content": "法甲"
    },
    {
      "content": "霍建華"
    },
    {
      "content": "man city vs leeds"
    },
    {
      "content": "barcelona đấu với alavés"
    },
    {
      "content": "盧廣仲"
    },
    {
      "content": "曼城"
    }
  ]
}