{
  "updated": "2025-11-19T23:47:25.364Z",
  "trends": [
    {
      "content": "輝達盤後"
    },
    {
      "content": "nvda stock"
    },
    {
      "content": "tsm stock"
    },
    {
      "content": "美光"
    },
    {
      "content": "美光股價"
    },
    {
      "content": "mu stock"
    },
    {
      "content": "道瓊指數"
    },
    {
      "content": "夜盤"
    },
    {
      "content": "鉅亨網"
    },
    {
      "content": "instagram"
    },
    {
      "content": "博通股價"
    },
    {
      "content": "費城半導體"
    },
    {
      "content": "費城半導體指數"
    },
    {
      "content": "今彩539"
    }
  ]
}