{
  "updated": "2026-06-19T19:17:09.170Z",
  "trends": [
    {
      "content": "美國 對 澳洲"
    },
    {
      "content": "世 足"
    },
    {
      "content": "交通安全"
    },
    {
      "content": "iem cologne major 2026"
    },
    {
      "content": "drake"
    },
    {
      "content": "donk"
    },
    {
      "content": "交通部中央氣象署"
    },
    {
      "content": "浪 姐 7"
    },
    {
      "content": "prx vs edg"
    },
    {
      "content": "亞歷克莎·埃亞拉"
    },
    {
      "content": "半導體"
    },
    {
      "content": "藤井風"
    },
    {
      "content": "包上恩"
    },
    {
      "content": "判決書"
    },
    {
      "content": "vct"
    },
    {
      "content": "曾敬驊"
    },
    {
      "content": "valorant"
    }
  ]
}