{
  "updated": "2026-06-07T18:53:40.248Z",
  "trends": [
    {
      "content": "法網"
    },
    {
      "content": "勒布朗·詹姆斯"
    },
    {
      "content": "王文祥"
    },
    {
      "content": "alexander zverev"
    },
    {
      "content": "劉亦菲"
    },
    {
      "content": "胡楓"
    },
    {
      "content": "roland garros"
    },
    {
      "content": "kimi antonelli"
    },
    {
      "content": "地震"
    },
    {
      "content": "豪雨假"
    },
    {
      "content": "lewis hamilton"
    },
    {
      "content": "hadjar"
    },
    {
      "content": "charles leclerc"
    }
  ]
}