{
  "updated": "2026-05-20T09:52:37.332Z",
  "trends": [
    {
      "content": "三振"
    },
    {
      "content": "康 康"
    },
    {
      "content": "蘇小軒"
    },
    {
      "content": "臺北 市長"
    },
    {
      "content": "0-18歲每月5000"
    },
    {
      "content": "黃國昌"
    },
    {
      "content": "in89"
    },
    {
      "content": "長榮 海運"
    },
    {
      "content": "蘇巧慧"
    },
    {
      "content": "老農 津貼"
    },
    {
      "content": "曹興誠"
    },
    {
      "content": "周玉蔻"
    },
    {
      "content": "黃婼馡"
    },
    {
      "content": "校長"
    },
    {
      "content": "寶 可 夢 公司"
    },
    {
      "content": "林昱珉"
    },
    {
      "content": "李燕"
    },
    {
      "content": "美國國稅局"
    },
    {
      "content": "台北科技大學"
    },
    {
      "content": "光 寶 科技"
    },
    {
      "content": "悠遊卡"
    },
    {
      "content": "macos"
    },
    {
      "content": "鴻華先進"
    },
    {
      "content": "上訴"
    },
    {
      "content": "臻 鼎 ky"
    }
  ]
}