{
  "updated": "2025-11-22T19:23:30.467Z",
  "trends": [
    {
      "content": "紐卡索聯 對 曼城"
    },
    {
      "content": "曼城"
    },
    {
      "content": "ลิเวอร์พูล พบ ฟอเรสต์"
    },
    {
      "content": "華莎"
    },
    {
      "content": "liverpool vs nottingham forest"
    },
    {
      "content": "barcelona vs bilbao"
    },
    {
      "content": "娜璉"
    },
    {
      "content": "第一銀行"
    },
    {
      "content": "利物浦"
    },
    {
      "content": "義甲"
    },
    {
      "content": "barcelona đấu với ath. bilbao"
    },
    {
      "content": "模範計程車"
    },
    {
      "content": "最佳男主角"
    },
    {
      "content": "once"
    },
    {
      "content": "中島美嘉"
    }
  ]
}