{
  "updated": "2025-11-22T15:47:01.557Z",
  "trends": [
    {
      "content": "曾敬驊"
    },
    {
      "content": "張國柱"
    },
    {
      "content": "地母電影"
    },
    {
      "content": "陳雪甄"
    },
    {
      "content": "眾生相"
    },
    {
      "content": "大濛故事"
    },
    {
      "content": "孫盛希"
    },
    {
      "content": "馬士媛"
    },
    {
      "content": "戴佩妮"
    },
    {
      "content": "李竺芯"
    },
    {
      "content": "巴塞隆納 對 畢爾包"
    },
    {
      "content": "陳意涵"
    },
    {
      "content": "利物浦 對 諾丁漢森林"
    },
    {
      "content": "侯孝賢"
    },
    {
      "content": "金士傑"
    },
    {
      "content": "ลิเวอร์พูล พบ ฟอเรสต์"
    },
    {
      "content": "林嘉欣"
    },
    {
      "content": "twice 大巨蛋"
    },
    {
      "content": "barcelona vs bilbao"
    },
    {
      "content": "楊貴媚"
    },
    {
      "content": "志效"
    },
    {
      "content": "拜仁慕尼黑 對 弗萊堡"
    },
    {
      "content": "陳匡怡"
    },
    {
      "content": "burnley vs chelsea"
    },
    {
      "content": "吳淑敏"
    }
  ]
}