{
  "updated": "2026-04-25T11:52:05.663Z",
  "trends": [
    {
      "content": "戰鬥機"
    },
    {
      "content": "陳妍希"
    },
    {
      "content": "投資 人"
    },
    {
      "content": "臺北大巨蛋"
    },
    {
      "content": "经济"
    },
    {
      "content": "成功 嶺"
    },
    {
      "content": "翁虹"
    },
    {
      "content": "孫鵬"
    },
    {
      "content": "周蕙"
    },
    {
      "content": "軍事演習"
    },
    {
      "content": "半导体"
    },
    {
      "content": "輝 達"
    },
    {
      "content": "麥 可 貝 瑞"
    },
    {
      "content": "台北車站"
    },
    {
      "content": "宜蘭縣"
    },
    {
      "content": "慈善"
    },
    {
      "content": "奪命願望"
    },
    {
      "content": "黃澤林"
    },
    {
      "content": "林安可"
    },
    {
      "content": "yen intervention risk"
    },
    {
      "content": "motogp"
    },
    {
      "content": "小巨蛋演唱會"
    },
    {
      "content": "美國職棒"
    },
    {
      "content": "新北美術館煙火"
    },
    {
      "content": "范瑋琪"
    }
  ]
}