{
  "updated": "2026-07-11T12:37:45.939Z",
  "trends": [
    {
      "content": "颱風 垃圾 車"
    },
    {
      "content": "7/12停班停課"
    },
    {
      "content": "政治"
    },
    {
      "content": "李 雅英"
    },
    {
      "content": "巴 威 中國"
    },
    {
      "content": "阮慕驊"
    },
    {
      "content": "光通訊"
    },
    {
      "content": "sk 海 力士"
    },
    {
      "content": "二 伯 抄襲 對比"
    },
    {
      "content": "周子 瑜"
    },
    {
      "content": "富國島"
    },
    {
      "content": "金 特務 本色 回歸"
    },
    {
      "content": "水 情"
    },
    {
      "content": "速克達"
    },
    {
      "content": "英國航空"
    },
    {
      "content": "交割"
    },
    {
      "content": "本益比"
    },
    {
      "content": "泰安觀止"
    },
    {
      "content": "請世界吃桌"
    },
    {
      "content": "颱風假桃園"
    },
    {
      "content": "joeman"
    },
    {
      "content": "中时新闻网"
    },
    {
      "content": "lcs"
    },
    {
      "content": "岡本和真"
    },
    {
      "content": "lyon lol"
    }
  ]
}