{
  "updated": "2026-07-14T10:22:14.367Z",
  "trends": [
    {
      "content": "孫 鵬"
    },
    {
      "content": "市長"
    },
    {
      "content": "茲卡病毒"
    },
    {
      "content": "命運 好 好玩"
    },
    {
      "content": "阮慕驊"
    },
    {
      "content": "劉樂妍"
    },
    {
      "content": "航空"
    },
    {
      "content": "賴 瑞隆"
    },
    {
      "content": "曾智希"
    },
    {
      "content": "華 邦 電子"
    },
    {
      "content": "中華民國外交部"
    },
    {
      "content": "台灣"
    },
    {
      "content": "虎航"
    },
    {
      "content": "裁判"
    },
    {
      "content": "彩票"
    },
    {
      "content": "新竹音樂教室"
    },
    {
      "content": "加權指數"
    },
    {
      "content": "子 瑜"
    },
    {
      "content": "金秀賢"
    },
    {
      "content": "cpo"
    },
    {
      "content": "高壓脊"
    },
    {
      "content": "8027"
    },
    {
      "content": "股價"
    },
    {
      "content": "國巨 為什麼 一直 跌"
    },
    {
      "content": "馬自達cx-5"
    }
  ]
}