{
  "updated": "2026-04-11T11:43:40.701Z",
  "trends": [
    {
      "content": "詹江村"
    },
    {
      "content": "資本 利得"
    },
    {
      "content": "好 市 多"
    },
    {
      "content": "兵工廠 對 伯恩茅斯"
    },
    {
      "content": "李國煌"
    },
    {
      "content": "中华邮政"
    },
    {
      "content": "伺服 器"
    },
    {
      "content": "arsenal vs bournemouth"
    },
    {
      "content": "亞洲羽球錦標賽"
    },
    {
      "content": "arsenal đấu với bournemouth"
    },
    {
      "content": "黄国昌"
    },
    {
      "content": "导弹"
    },
    {
      "content": "寬限期"
    },
    {
      "content": "昏迷"
    },
    {
      "content": "咖啡"
    },
    {
      "content": "三大日"
    },
    {
      "content": "劉芙豪"
    },
    {
      "content": "富邦勇士"
    },
    {
      "content": "翁鈺鈞"
    },
    {
      "content": "马自达"
    },
    {
      "content": "潘健成"
    },
    {
      "content": "陳盈潔"
    },
    {
      "content": "rapidus"
    },
    {
      "content": "台湾中油"
    },
    {
      "content": "美國職棒"
    }
  ]
}