{
  "updated": "2025-11-24T03:47:02.572Z",
  "trends": [
    {
      "content": "爵士 對 湖人"
    },
    {
      "content": "太陽 對 馬刺"
    },
    {
      "content": "雷霆 對 拓荒者"
    },
    {
      "content": "msci 調整"
    },
    {
      "content": "好事多黑五"
    },
    {
      "content": "jazz vs lakers"
    },
    {
      "content": "天琴颱風"
    },
    {
      "content": "林岱安"
    },
    {
      "content": "2330"
    },
    {
      "content": "0050"
    },
    {
      "content": "金山電"
    },
    {
      "content": "暴龍 對 籃網"
    },
    {
      "content": "皇池"
    },
    {
      "content": "大盤指數"
    },
    {
      "content": "老鷹 對 黃蜂"
    },
    {
      "content": "華邦電股價"
    },
    {
      "content": "台積電股票"
    },
    {
      "content": "日本股市休市"
    },
    {
      "content": "創意"
    },
    {
      "content": "日經指數"
    },
    {
      "content": "金居"
    },
    {
      "content": "大盤"
    },
    {
      "content": "8043"
    },
    {
      "content": "無人機"
    },
    {
      "content": "光寶科"
    }
  ]
}