{
  "updated": "2026-02-28T10:54:16.737Z",
  "trends": [
    {
      "content": "比特幣"
    },
    {
      "content": "美伊戰爭"
    },
    {
      "content": "美國伊朗最新消息"
    },
    {
      "content": "蔡正元"
    },
    {
      "content": "巴林"
    },
    {
      "content": "btc"
    },
    {
      "content": "bbc"
    },
    {
      "content": "味全龍"
    },
    {
      "content": "2026鹿耳門煙火時間"
    },
    {
      "content": "tomorrowland"
    },
    {
      "content": "比特幣價格"
    },
    {
      "content": "陽岱鋼"
    },
    {
      "content": "btc usd"
    },
    {
      "content": "台中燈會"
    },
    {
      "content": "oisix 新潟"
    },
    {
      "content": "bingo bingo 玩法"
    },
    {
      "content": "施振榮"
    },
    {
      "content": "gold price"
    },
    {
      "content": "杜拜"
    },
    {
      "content": "以色列打伊朗"
    },
    {
      "content": "bahrain"
    },
    {
      "content": "宮崎機場"
    },
    {
      "content": "教育部"
    },
    {
      "content": "台北燈會 2026"
    },
    {
      "content": "虎頭山燈會"
    }
  ]
}