{
  "updated": "2025-11-02T03:37:20.741Z",
  "trends": [
    {
      "content": "世界大賽"
    },
    {
      "content": "mlb直播"
    },
    {
      "content": "mlb"
    },
    {
      "content": "mlb live"
    },
    {
      "content": "塞爾提克 對 火箭"
    },
    {
      "content": "snell"
    },
    {
      "content": "大谷翔平"
    },
    {
      "content": "棒球"
    },
    {
      "content": "world series"
    },
    {
      "content": "傑夫·霍夫曼"
    },
    {
      "content": "mlb 直播 免費"
    },
    {
      "content": "bo bichette"
    },
    {
      "content": "yesavage"
    },
    {
      "content": "愛爾達"
    },
    {
      "content": "多倫多"
    },
    {
      "content": "mlb 世界 大賽 線上 看 免費"
    },
    {
      "content": "ernie clement"
    },
    {
      "content": "直播吧"
    },
    {
      "content": "mlb."
    },
    {
      "content": "max scherzer"
    },
    {
      "content": "道奇 直播"
    },
    {
      "content": "glasnow"
    },
    {
      "content": "台中市民野餐日"
    },
    {
      "content": "西語老師"
    },
    {
      "content": "蘇丹"
    }
  ]
}