{
  "updated": "2025-12-31T18:57:13.457Z",
  "trends": [
    {
      "content": "台東縣長"
    },
    {
      "content": "d社元旦情侶"
    },
    {
      "content": "new year's day"
    },
    {
      "content": "具荷拉"
    },
    {
      "content": "李川"
    },
    {
      "content": "饒慶鈴"
    },
    {
      "content": "beast"
    },
    {
      "content": "王世堅"
    },
    {
      "content": "dispatch"
    },
    {
      "content": "nba直播"
    },
    {
      "content": "本鄉奏多"
    },
    {
      "content": "黃子韜"
    },
    {
      "content": "阿密特"
    },
    {
      "content": "楠木ともり"
    },
    {
      "content": "高雄"
    },
    {
      "content": "chivalry 2"
    },
    {
      "content": "倒數"
    },
    {
      "content": "總統府升旗"
    },
    {
      "content": "blackpink"
    },
    {
      "content": "元旦活動"
    },
    {
      "content": "鳥巢式共育"
    },
    {
      "content": "為什麼跨年要吃葡萄"
    },
    {
      "content": "sf"
    },
    {
      "content": "台中跨年壓軸"
    },
    {
      "content": "潘瑋柏"
    }
  ]
}