{
  "updated": "2025-11-02T19:21:51.167Z",
  "trends": [
    {
      "content": "金豬食堂"
    },
    {
      "content": "曼城 對 伯恩茅斯"
    },
    {
      "content": "barcelona vs elche"
    },
    {
      "content": "man city vs bournemouth"
    },
    {
      "content": "巴塞隆納 對 埃爾切"
    },
    {
      "content": "銀魂"
    },
    {
      "content": "周杰倫王子"
    },
    {
      "content": "硫化氫中毒"
    },
    {
      "content": "vladimir guerrero"
    },
    {
      "content": "西漢姆聯 對 紐卡索聯"
    },
    {
      "content": "普發登記"
    },
    {
      "content": "vladimir guerrero jr"
    }
  ]
}