{
  "updated": "2026-01-02T06:49:41.164Z",
  "trends": [
    {
      "content": "國王 對 塞爾提克"
    },
    {
      "content": "國民法官"
    },
    {
      "content": "鄭亦真"
    },
    {
      "content": "星巴克買一送一"
    },
    {
      "content": "李凱爾"
    },
    {
      "content": "3624"
    },
    {
      "content": "3037 欣興"
    },
    {
      "content": "華新科"
    },
    {
      "content": "金正恩"
    },
    {
      "content": "tesla"
    },
    {
      "content": "2327"
    },
    {
      "content": "喬爾·恩比德"
    },
    {
      "content": "華邦"
    },
    {
      "content": "台特化"
    }
  ]
}