{
  "updated": "2025-12-08T17:33:33.495Z",
  "trends": [
    {
      "content": "日本地震"
    },
    {
      "content": "nhk"
    },
    {
      "content": "日本地震速報"
    },
    {
      "content": "japan earthquake"
    },
    {
      "content": "ios 26.2"
    },
    {
      "content": "范瑋琪"
    },
    {
      "content": "李燕"
    },
    {
      "content": "柯震東"
    },
    {
      "content": "金高銀"
    },
    {
      "content": "卡利消"
    },
    {
      "content": "仙台"
    },
    {
      "content": "東京"
    }
  ]
}