{
  "updated": "2026-05-12T17:36:04.918Z",
  "trends": [
    {
      "content": "美股"
    },
    {
      "content": "金"
    },
    {
      "content": "江宏恩"
    },
    {
      "content": "夜 盤"
    },
    {
      "content": "台灣 積 體 電路 製造 股份 有限 公司"
    },
    {
      "content": "電信"
    },
    {
      "content": "vix"
    },
    {
      "content": "費城半導體"
    },
    {
      "content": "2357"
    },
    {
      "content": "柏承科技"
    },
    {
      "content": "王美惠"
    },
    {
      "content": "one ui 8.5"
    },
    {
      "content": "nasdaq"
    },
    {
      "content": "川普訪中"
    },
    {
      "content": "金材昱"
    },
    {
      "content": "文化內容策進院"
    },
    {
      "content": "qubt"
    },
    {
      "content": "神達"
    },
    {
      "content": "美股即時"
    },
    {
      "content": "興富發"
    },
    {
      "content": "亞歷山大·茲維列夫"
    },
    {
      "content": "진에어 입사 연기"
    },
    {
      "content": "三重新聞"
    }
  ]
}